[
  {
    "date": "2/9",
    "val": 300,
    "place": "",
    "memo": "kaigi_sanmarc_umeda"
  },
  {
    "date": "2/13",
    "val": 430,
    "place": "",
    "memo": "kaigi_sanmarc_umeda"
  },
  {
    "date": "2/21",
    "val": 300,
    "place": "",
    "memo": "kaigi_sanmarc_umeda"
  },
  {
    "date": "2/22",
    "val": 300,
    "place": "",
    "memo": "kaigi_sanmarc_umeda"
  },
  {
    "date": "7/12",
    "val": 300,
    "place": "",
    "memo": "kaigi_sanmarc_umeda"
  },
  {
    "date": "8/30",
    "val": 300,
    "place": "",
    "memo": "kaigi_sanmarc_umeda"
  },
  {
    "date": "9/8",
    "val": 300,
    "place": "",
    "memo": "kaigi_sanmarc_umeda"
  },
  {
    "date": "9/15",
    "val": 300,
    "place": "",
    "memo": "kaigi_sanmarc_umeda"
  },
  {
    "date": "9/16",
    "val": 300,
    "place": "",
    "memo": "kaigi_sanmarc_umeda"
  },
  {
    "date": "11/26",
    "val": 300,
    "place": "",
    "memo": "kaigi_sanmarc_umeda"
  }
]