[
  {
    "date": "1/8",
    "val": 1620,
    "place": "",
    "memo": "西梅田__kaigi_medicalcafepopeye_umeda"
  },
  {
    "date": "2/5",
    "val": 4940,
    "place": "",
    "memo": "泉の広場店(paypay売上票のみ）__kaigi_medicalcafepopeye_umeda"
  },
  {
    "date": "6/11",
    "val": 5280,
    "place": "",
    "memo": "太融寺店__kaigi_medicalcafepopeye_umeda"
  },
  {
    "date": "8/16",
    "val": 1680,
    "place": "",
    "memo": "西梅田__kaigi_medicalcafepopeye_umeda"
  },
  {
    "date": "11/3",
    "val": 5280,
    "place": "",
    "memo": "泉の広場店__kaigi_medicalcafepopeye_umeda"
  },
  {
    "date": "11/12",
    "val": 6300,
    "place": "",
    "memo": "泉の広場店__kaigi_medicalcafepopeye_umeda"
  },
  {
    "date": "11/18",
    "val": 3100,
    "place": "",
    "memo": "泉の広場店(paypay売上表のみ）__kaigi_medicalcafepopeye_umeda"
  },
  {
    "date": "12/16",
    "val": 2120,
    "place": "",
    "memo": "泉の広場店__kaigi_medicalcafepopeye_umeda"
  },
  {
    "date": "12/24",
    "val": 5280,
    "place": "",
    "memo": "泉の広場店__kaigi_medicalcafepopeye_umeda"
  },
  {
    "date": "12/28",
    "val": 5280,
    "place": "",
    "memo": "泉の広場店__kaigi_medicalcafepopeye_umeda"
  }
]